pyjolt/__init__.py
pyjolt/base_extension.py
pyjolt/configuration_base.py
pyjolt/http_methods.py
pyjolt/http_statuses.py
pyjolt/logger.py
pyjolt/media_types.py
pyjolt/middleware.py
pyjolt/open_api.py
pyjolt/pyjolt.py
pyjolt/request.py
pyjolt/response.py
pyjolt/router.py
pyjolt/static.py
pyjolt/utilities.py
pyjolt/ai_interface/__init__.py
pyjolt/ai_interface/ai_interface.py
pyjolt/ai_interface/embeddings.py
pyjolt/ai_interface/database_types/__init__.py
pyjolt/ai_interface/database_types/vector_column.py
pyjolt/auth/__init__.py
pyjolt/auth/authentication.py
pyjolt/caching/__init__.py
pyjolt/caching/cache.py
pyjolt/caching/backends/__init__.py
pyjolt/caching/backends/base_cache_backend.py
pyjolt/caching/backends/memory_cache_backend.py
pyjolt/caching/backends/redis_cache_backend.py
pyjolt/caching/backends/sqlite_cache_backend.py
pyjolt/cli/__init__.py
pyjolt/cli/cli.py
pyjolt/cli/cli_controller.py
pyjolt/cli/new_project.py
pyjolt/cli/templates/new_project/cli.py
pyjolt/cli/templates/new_project/run.py
pyjolt/cli/templates/new_project/app/__init__.py
pyjolt/cli/templates/new_project/app/authentication.py
pyjolt/cli/templates/new_project/app/configs.py
pyjolt/cli/templates/new_project/app/extensions.py
pyjolt/cli/templates/new_project/app/api/example_api/__init__.py
pyjolt/cli/templates/new_project/app/api/example_api/example_api.py
pyjolt/cli/templates/new_project/app/api/exceptions/__init__.py
pyjolt/cli/templates/new_project/app/api/exceptions/exception_handler.py
pyjolt/cli/templates/new_project/app/api/models/__init__.py
pyjolt/cli/templates/new_project/app/api/models/example_model.py
pyjolt/cli/templates/new_project/app/cli/cli_controller.py
pyjolt/cli/templates/new_project/app/tests/__init__.py
pyjolt/cli/templates/new_project/app/tests/conftest.py
pyjolt/cli/templates/new_project/app/tests/test_example_api.py
pyjolt/controller/__init__.py
pyjolt/controller/controller.py
pyjolt/controller/decorators.py
pyjolt/controller/utilities.py
pyjolt-0.91.10.dist-info/METADATA
pyjolt-0.91.10.dist-info/WHEEL
pyjolt-0.91.10.dist-info/entry_points.txt
pyjolt-0.91.10.dist-info/licenses/LICENSE
pyjolt-0.91.10.dist-info/RECORD
